__init__.py
kystdatahuset/__init__.py
kystdatahuset/ais.py
kystdatahuset/api_client.py
kystdatahuset/auth.py
kystdatahuset/const.py
kystdatahuset/file_storage.py
kystdatahuset/logging.py
kystdatahuset/voyage.py
kystdatahuset/models/AuthData.py
kystdatahuset/models/FileListing.py
kystdatahuset/models/WebServiceResponse.py
kystdatahuset/models/__init__.py
kystdatahuset/types/PandasFrequency.py
kystdatahuset/types/UploadFileType.py
kystdatahuset/types/__init__.py
kystdatahuset/utils/__init__.py
kystdatahuset/utils/_date_range.py
kystdatahuset/utils/_slice_polygon_to_grid.py
kystdatahuset_python_lib-0.9.7.dist-info/licenses/LICENSE
kystdatahuset_python_lib-0.9.7.dist-info/METADATA
kystdatahuset_python_lib-0.9.7.dist-info/WHEEL
kystdatahuset_python_lib-0.9.7.dist-info/top_level.txt
kystdatahuset_python_lib-0.9.7.dist-info/RECORD
