Metadata-Version: 2.4
Name: kystdatahuset-python-lib
Version: 0.9.7
Summary: A python library for accessing and querying data from Kystdatahuset
Author-email: Kystdatahuset developer team <support@kystdatahuset.no>, "(Stein) Runar Bergheim" <runar.bergheim@avinet.no>, Sigve Bergh <sigve.bergh@kystverket.no>, Hermann Klaus Kurt von Lupfert <hermann.lupfert@kystverket.no>
Maintainer-email: Kystdatahuset developer team <support@kystdatahuset.no>
License-Expression: MIT
Project-URL: Homepage, https://github.com/Kystverket/kystdatahuset-python-lib
Project-URL: Repository, https://github.com/Kystverket/kystdatahuset-python-lib
Project-URL: Issues, https://github.com/Kystverket/kystdatahuset-python-lib/issues
Keywords: spatial,analytics,visualization,geodata
Classifier: Development Status :: 4 - Beta
Classifier: Intended Audience :: Developers
Classifier: Topic :: Software Development :: Libraries
Classifier: Topic :: Scientific/Engineering :: Information Analysis
Classifier: Programming Language :: Python :: 3.10
Requires-Python: >=3.9
License-File: LICENSE
Requires-Dist: numpy>=1.24
Requires-Dist: pandas>=2.0
Requires-Dist: pydantic>=2.0
Requires-Dist: requests>=2.28
Requires-Dist: shapely>=2.0
Requires-Dist: tqdm>=4.65
Dynamic: license-file
